Tool.py
ljxtestlib/__init__.py
ljxtestlib/ljxlibone.py
ljxtestlib-1.0.0.dist-info/LICENSE.txt
ljxtestlib-1.0.0.dist-info/METADATA
ljxtestlib-1.0.0.dist-info/WHEEL
ljxtestlib-1.0.0.dist-info/top_level.txt
ljxtestlib-1.0.0.dist-info/RECORD
