Metadata-Version: 2.1
Name: ljxtestlib
Version: 1.0.0
Summary: this is a niubi lix
Home-page: https://github.com/wangshunzi/Python_code
Author: Ljx
Author-email: 1169503322@qq.com
License: MIT
Platform: UNKNOWN
